PySEF-0.2.10.dist-info/METADATA
PySEF-0.2.10.dist-info/RECORD
PySEF-0.2.10.dist-info/WHEEL
PySEF-0.2.10.dist-info/top_level.txt
sef_dr/__init__.py
sef_dr/classification.py
sef_dr/datasets.py
sef_dr/kernel.py
sef_dr/linear.py
sef_dr/sef_base.py
sef_dr/similarity.py
sef_dr/targets.py
sef_dr/version.py
