Metadata-Version: 2.1
Name: PySEF
Version: 0.2.10
Summary: Package that implements the Similarity Embedding Framework on top of the PyTorch library.
Home-page: https://github.com/passalis/sef
Author: N. Passalis
Author-email: passalis@csd.auth.gr
License: LICENSE.txt
Platform: UNKNOWN
Requires-Dist: scikit-learn (>=0.19.1)
Requires-Dist: numpy (>=1.13.3)
Requires-Dist: scipy (>=1.0.0)
Requires-Dist: torchvision (>=0.2.0)
